requirements.txt
setup.py
mac_speech_commands/__init__.py
mac_speech_commands.egg-info/PKG-INFO
mac_speech_commands.egg-info/SOURCES.txt
mac_speech_commands.egg-info/dependency_links.txt
mac_speech_commands.egg-info/top_level.txt