Metadata-Version: 2.1
Name: mac-speech-commands
Version: 2020.7.1
Summary: extend macOS speech commands
Home-page: https://github.com/andrewp-as-is/mac-speech-commands.py
License: Unlicense
Keywords: speech tts
Platform: UNKNOWN
Classifier: License :: Public Domain
Classifier: Operating System :: MacOS
Classifier: Programming Language :: Python :: 3
